import_export_extensions/__init__.py
import_export_extensions/admin/__init__.py
import_export_extensions/admin/forms/__init__.py
import_export_extensions/admin/forms/export_job_admin_form.py
import_export_extensions/admin/forms/import_admin_form.py
import_export_extensions/admin/forms/import_job_admin_form.py
import_export_extensions/admin/mixins/__init__.py
import_export_extensions/admin/mixins/base_mixin.py
import_export_extensions/admin/mixins/export_mixin.py
import_export_extensions/admin/mixins/import_export_mixin.py
import_export_extensions/admin/mixins/import_mixin.py
import_export_extensions/admin/mixins/types.py
import_export_extensions/admin/model_admins/__init__.py
import_export_extensions/admin/model_admins/export_job_admin.py
import_export_extensions/admin/model_admins/import_job_admin.py
import_export_extensions/admin/model_admins/mixins.py
import_export_extensions/admin/widgets.py
import_export_extensions/api/__init__.py
import_export_extensions/api/mixins/__init__.py
import_export_extensions/api/mixins/common.py
import_export_extensions/api/mixins/export_mixins.py
import_export_extensions/api/mixins/import_mixins.py
import_export_extensions/api/serializers/__init__.py
import_export_extensions/api/serializers/export_job.py
import_export_extensions/api/serializers/import_job.py
import_export_extensions/api/serializers/import_job_details.py
import_export_extensions/api/serializers/progress.py
import_export_extensions/api/views/__init__.py
import_export_extensions/api/views/export_job.py
import_export_extensions/api/views/import_job.py
import_export_extensions/apps.py
import_export_extensions/fields.py
import_export_extensions/forms.py
import_export_extensions/migrations/0001_initial.py
import_export_extensions/migrations/0002_alter_exportjob_export_status.py
import_export_extensions/migrations/0003_importjob_skip_parse_step.py
import_export_extensions/migrations/0004_alter_exportjob_created_by_and_more.py
django_import_export_extensions-1.9.2.dist-info/METADATA
django_import_export_extensions-1.9.2.dist-info/WHEEL
django_import_export_extensions-1.9.2.dist-info/licenses/AUTHORS.rst
django_import_export_extensions-1.9.2.dist-info/licenses/LICENSE
django_import_export_extensions-1.9.2.dist-info/RECORD
