Metadata-Version: 2.4
Name: django-import-export-extensions
Version: 1.9.2
Summary: Extend functionality of `django-import-export`
License: MIT
License-File: AUTHORS.rst
License-File: LICENSE
Keywords: python,json,django,csv,xlsx,celery,import_export,django_import_export_extensions
Author: Saritasa
Author-email: pypi@saritasa.com
Maintainer: Nikita Azanov
Maintainer-email: nikita.azanov@saritasa.com
Requires-Python: >=3.10,<4.0
Classifier: Development Status :: 5 - Production/Stable
Classifier: Framework :: Django
Classifier: Framework :: Django :: 4.2
Classifier: Framework :: Django :: 5.0
Classifier: Framework :: Django :: 5.1
Classifier: Framework :: Django :: 5.2
Classifier: Intended Audience :: Developers
Classifier: License :: OSI Approved :: MIT License
Classifier: Operating System :: OS Independent
Classifier: Programming Language :: Python
Classifier: Programming Language :: Python :: 3
Classifier: Programming Language :: Python :: 3.10
Classifier: Programming Language :: Python :: 3.11
Classifier: Programming Language :: Python :: 3.12
Classifier: Programming Language :: Python :: 3.13
Classifier: Programming Language :: Python :: 3.14
Classifier: Programming Language :: Python :: 3 :: Only
Classifier: Topic :: Software Development
Requires-Dist: celery[redis] (>=5.4.0,<6.0.0)
Requires-Dist: django (>=4.2)
Requires-Dist: django-extensions (>=3.2.3,<5.0.0)
Requires-Dist: django-filter (>=24.3,<26.0)
Requires-Dist: django-import-export[xls,xlsx] (>=4.2)
Requires-Dist: django-picklefield (>=3.2,<4.0)
Requires-Dist: djangorestframework (>=3.15.2,<4.0.0)
Requires-Dist: drf-spectacular (<0.30.0)
Requires-Dist: requests (>=2.32.3,<3.0.0)
Project-URL: Documentation, https://django-import-export-extensions.readthedocs.io
Project-URL: Repository, https://github.com/saritasa-nest/django-import-export-extensions
